EpsilonCode-1.3.0.data/scripts/epsilon.sh
epsilonCode/__init__.py
epsilonCode/code-gen.py
epsilonCode/debug.py
epsilonCode/getcode.py
epsilonCode/getdebug.py
EpsilonCode-1.3.0.dist-info/LICENSE
EpsilonCode-1.3.0.dist-info/METADATA
EpsilonCode-1.3.0.dist-info/WHEEL
EpsilonCode-1.3.0.dist-info/top_level.txt
EpsilonCode-1.3.0.dist-info/RECORD
